Metadata-Version: 2.1
Name: odoo14-addon-sale_planned_consumed_date
Version: 14.0.0.1.1.dev4
Summary: Sale planned consumed date
Home-page: https://github.com/OCA/stock-logistics-workflow
Author: Pierre Verkest <pierreverkest84@gmail.com>, Odoo Community Association (OCA)
Author-email: support@odoo-community.org
License: AGPL-3
Classifier: Programming Language :: Python
Classifier: Framework :: Odoo
Classifier: Framework :: Odoo :: 14.0
Classifier: License :: OSI Approved :: GNU Affero General Public License v3
Classifier: Development Status :: 4 - Beta
Requires-Python: >=3.6
Requires-Dist: odoo14-addon-stock-move-planned-consumed-date
Requires-Dist: odoo<14.1dev,>=14.0a
